aiothreading/__init__.py
aiothreading/__version__.py
aiothreading/core.py
aiothreading/pool.py
aiothreading/scheduler.py
aiothreading/types.py
aiothreading-0.1.6.dist-info/licenses/LICENSE
aiothreading-0.1.6.dist-info/METADATA
aiothreading-0.1.6.dist-info/WHEEL
aiothreading-0.1.6.dist-info/top_level.txt
aiothreading-0.1.6.dist-info/RECORD
