Metadata-Version: 2.4
Name: aiothreading
Version: 0.1.6
Summary: AsyncIO version of the standard threading module
Author: x42005e1f
Author-email: Vizonex <VizonexBusiness@gmail.com>
Project-URL: homepage, https://github.com/Vizonex/aiothreading
Project-URL: repository, https://github.com/Vizonex/aiothreading.git
Keywords: aiothreading,threading,asyncio
Classifier: Framework :: AsyncIO
Classifier: Intended Audience :: Developers
Classifier: Topic :: Software Development :: Libraries
Classifier: Programming Language :: Python :: 3.10
Classifier: Programming Language :: Python :: 3.11
Classifier: Programming Language :: Python :: 3.12
Classifier: Programming Language :: Python :: 3.13
Classifier: Programming Language :: Python :: 3.14
Requires-Python: >=3.10
License-File: LICENSE
Requires-Dist: aiologic>=0.15.0
Requires-Dist: deprecation-alias>=0.3.0
Dynamic: license-file
